README.md
setup.py
tap_mavenlink/__init__.py
tap_mavenlink/cache.py
tap_mavenlink/client.py
tap_mavenlink/config.py
tap_mavenlink/state.py
tap_mavenlink.egg-info/PKG-INFO
tap_mavenlink.egg-info/SOURCES.txt
tap_mavenlink.egg-info/dependency_links.txt
tap_mavenlink.egg-info/entry_points.txt
tap_mavenlink.egg-info/requires.txt
tap_mavenlink.egg-info/top_level.txt
tap_mavenlink/schemas/account_memberships.json
tap_mavenlink/schemas/assignments.json
tap_mavenlink/schemas/custom_fields.json
tap_mavenlink/schemas/estimate_scenario_resources.json
tap_mavenlink/schemas/estimate_scenarios.json
tap_mavenlink/schemas/estimates.json
tap_mavenlink/schemas/expense_categories.json
tap_mavenlink/schemas/expenses.json
tap_mavenlink/schemas/invoices.json
tap_mavenlink/schemas/posts.json
tap_mavenlink/schemas/stories.json
tap_mavenlink/schemas/time_entries.json
tap_mavenlink/schemas/users.json
tap_mavenlink/schemas/workspace_allocations.json
tap_mavenlink/schemas/workspace_custom_field_values.json
tap_mavenlink/schemas/workspace_groups.json
tap_mavenlink/schemas/workspaces.json
tap_mavenlink/streams/__init__.py
tap_mavenlink/streams/account_memberships.py
tap_mavenlink/streams/assignments.py
tap_mavenlink/streams/base.py
tap_mavenlink/streams/custom_fields.py
tap_mavenlink/streams/estimates.py
tap_mavenlink/streams/estimates_resources.py
tap_mavenlink/streams/estimates_scenarios.py
tap_mavenlink/streams/expense_categories.py
tap_mavenlink/streams/expenses.py
tap_mavenlink/streams/invoices.py
tap_mavenlink/streams/posts.py
tap_mavenlink/streams/stories.py
tap_mavenlink/streams/time_entries.py
tap_mavenlink/streams/users.py
tap_mavenlink/streams/workspace_allocations.py
tap_mavenlink/streams/workspace_custom_field_values.py
tap_mavenlink/streams/workspace_groups.py
tap_mavenlink/streams/workspaces.py